idevops/__init__.py
idevops/aliased_group.py
idevops/ansible.cfg
idevops/aws.py
idevops/cli.py
idevops/data.yml
idevops/iserver.py
idevops/shell_wrapper.py
idevops/ssh.py
idevops/test.py
idevops/test_up.py
idevops/utils.py
idevops/version.py
idevops/ansible/__init__.py
idevops/ansible/ansible_playbook_runner.py
idevops/ansible/run_test.py
idevops/config/gen_keypair.go
idevops/config/genesis.yml.j2
idevops/config/iserver.yml.j2
idevops/playbook/say_hi.yml
idevops/playbooks/backup.yml
idevops/playbooks/clean.yml
idevops/playbooks/deploy.yml
idevops/playbooks/fetch_backup.yml
idevops/playbooks/genconfig.yml
idevops/playbooks/init.yml
idevops/playbooks/perform_test.yml
idevops/playbooks/reload.yml
idevops/playbooks/restart.yml
idevops/playbooks/restore.yml
idevops/playbooks/say_hi.yml
idevops/playbooks/start.yml
idevops/playbooks/stop.yml
idevops/playbooks/test.yml
idevops/playbooks/roles/builder/tasks/make.yml
idevops/playbooks/roles/builder/tasks/push_image.yml
idevops/playbooks/roles/iserver/defaults/main.yml
idevops/playbooks/roles/iserver/tasks/.gitignore
idevops/playbooks/roles/iserver/tasks/backup.yml
idevops/playbooks/roles/iserver/tasks/create_docker.yml
idevops/playbooks/roles/iserver/tasks/dd_test.yml
idevops/playbooks/roles/iserver/tasks/fetch_backup.yml
idevops/playbooks/roles/iserver/tasks/generate_config_locally.yml
idevops/playbooks/roles/iserver/tasks/init.yml
idevops/playbooks/roles/iserver/tasks/iperf_start.yml
idevops/playbooks/roles/iserver/tasks/iperf_stop.yml
idevops/playbooks/roles/iserver/tasks/iperf_test.yml
idevops/playbooks/roles/iserver/tasks/make.yml
idevops/playbooks/roles/iserver/tasks/ping_test.yml
idevops/playbooks/roles/iserver/tasks/purge_data.yml
idevops/playbooks/roles/iserver/tasks/restart_docker.yml
idevops/playbooks/roles/iserver/tasks/restore.yml
idevops/playbooks/roles/iserver/tasks/set_hosts.yml
idevops/playbooks/roles/iserver/tasks/start_docker.yml
idevops/playbooks/roles/iserver/tasks/stop_docker.yml
idevops-3.0.17.dist-info/LICENSE
idevops-3.0.17.dist-info/METADATA
idevops-3.0.17.dist-info/WHEEL
idevops-3.0.17.dist-info/entry_points.txt
idevops-3.0.17.dist-info/top_level.txt
idevops-3.0.17.dist-info/RECORD
