Metadata-Version: 2.1
Name: idevops
Version: 3.0.17
Summary: Build iost net within one button.
Home-page: https://github.com/iost-official/idevops
Author: Yuanyi
Author-email: yuanyi@iost.io
License: LGPLv3+
Platform: any
Classifier: Development Status :: 5 - Production/Stable
Classifier: Environment :: Console
Classifier: Intended Audience :: Developers
Classifier: License :: OSI Approved :: GNU Lesser General Public License v3 or later (LGPLv3+)
Classifier: Operating System :: POSIX
Classifier: Operating System :: MacOS
Classifier: Operating System :: Unix
Classifier: Operating System :: Microsoft :: Windows
Classifier: Programming Language :: Python
Classifier: Programming Language :: Python :: 2
Classifier: Programming Language :: Python :: 3
Classifier: Topic :: Software Development :: Libraries :: Python Modules
Requires-Dist: ansible
Requires-Dist: boto3
Requires-Dist: click
Requires-Dist: ptable
